mosaik_web/__init__.py
mosaik_web/mosaik.py
mosaik_web/server.py
mosaik_web/html/index.html
mosaik_web/html/media/d3.min.js
mosaik_web/html/media/main.css
mosaik_web/html/media/mosaik.js
mosaik_web/html/media/snord.json
mosaik_web-0.4.0.dist-info/DESCRIPTION.rst
mosaik_web-0.4.0.dist-info/METADATA
mosaik_web-0.4.0.dist-info/RECORD
mosaik_web-0.4.0.dist-info/WHEEL
mosaik_web-0.4.0.dist-info/entry_points.txt
mosaik_web-0.4.0.dist-info/metadata.json
mosaik_web-0.4.0.dist-info/top_level.txt
